{
    "video_metadata": {
        "id": 7540720764442430751,
        "time_created": "2025-08-21T01:28:07",
        "author_id": 7171936683896751147,
        "description": "Pretty easy! #looks #hard #not #numbers #trick #hack #sat #study #school #math #bigbraintutor #education #studytok ",
        "hashtags": [
            "looks",
            "hard",
            "not",
            "numbers",
            "trick",
            "hack",
            "sat",
            "study",
            "school",
            "math",
            "bigbraintutor",
            "education",
            "studytok"
        ],
        "mentions": null,
        "music_id": 7540720750181796639,
        "schedule_time": 0,
        "location_created": "US",
        "is_ad": false,
        "suggested_words": [
            "Math",
            "how to convert decimal to fraction",
            "Geometry Math"
        ],
        "diggcount": 28100,
        "sharecount": 1106,
        "commentcount": 165,
        "playcount": 471400,
        "collectcount": 8553,
        "repostcount": 0,
        "warn_info": [],
        "original_item": false,
        "offical_item": false,
        "secret": false,
        "for_friend": false,
        "digged": false,
        "item_comment_status": 0,
        "take_down": 0,
        "effect_stickers": [
            {
                "name": "3D Green Screen",
                "ID": "929306"
            }
        ],
        "private_item": false,
        "duet_enabled": true,
        "stitch_enabled": true,
        "stickers_on_item": [
            {
                "stickerText": [
                    "This looks hard \nbut it’s not"
                ],
                "stickerType": 4
            }
        ],
        "share_enabled": true,
        "comments": null,
        "duet_display": 0,
        "stitch_display": 0,
        "index_enabled": true,
        "diversification_labels": [
            "School Education",
            "Education",
            "Culture & Education & Technology"
        ],
        "diversification_id": 10068,
        "channel_tags": [],
        "keyword_tags": null,
        "is_ai_gc": false,
        "aigc_label_type": null,
        "ai_gc_description": null
    },
    "file_metadata": {
        "id": 7540720764442430751,
        "filepath": "test_folder/tiktok_7540720764442430751_*",
        "duration": 64,
        "height": 1024,
        "width": 576,
        "ratio": 540,
        "volume_loudness": -27.3,
        "volume_peak": 0.40738,
        "has_original_audio": true,
        "enable_audio_caption": true,
        "no_caption_reason": 1,
        "is_slide": false
    },
    "music_metadata": {
        "id": 7540720750181796639,
        "title": "original sound",
        "author_name": "The math tutor",
        "original": true,
        "schedule_search_time": 0,
        "collected": false,
        "precise_duration": {
            "preciseDuration": 64.862,
            "preciseShootDuration": 64.862,
            "preciseAuditionDuration": 64.862,
            "preciseVideoDuration": 64.862
        }
    },
    "author_metadata": {
        "id": 7171936683896751147,
        "username": "your.big.brain.tutor",
        "name": "The math tutor",
        "signature": "1.4M big brains!\nEmail: yourbigbraintutor@gmail.com",
        "create_time": 1669846719,
        "verified": false,
        "ftc": false,
        "relation": 0,
        "open_favorite": false,
        "comment_setting": 0,
        "duet_setting": 0,
        "stitch_setting": 0,
        "private_account": false,
        "secret": false,
        "is_ad_virtual": false,
        "download_setting": 0,
        "recommend_reason": "",
        "suggest_account_bind": false
    },
    "hashtags_metadata": [
        {
            "name": "looks",
            "id": 39054,
            "type": 1,
            "sub_type": 0,
            "is_commerce": false,
            "description": ""
        },
        {
            "name": "hard",
            "id": 12727,
            "type": 1,
            "sub_type": 0,
            "is_commerce": false,
            "description": ""
        },
        {
            "name": "not",
            "id": 5760,
            "type": 1,
            "sub_type": 0,
            "is_commerce": false,
            "description": ""
        },
        {
            "name": "numbers",
            "id": 28611,
            "type": 1,
            "sub_type": 0,
            "is_commerce": false,
            "description": ""
        },
        {
            "name": "trick",
            "id": 5332,
            "type": 1,
            "sub_type": 0,
            "is_commerce": false,
            "description": ""
        },
        {
            "name": "hack",
            "id": 42566,
            "type": 1,
            "sub_type": 0,
            "is_commerce": false,
            "description": "Share those lifechanging hacks you can't live without"
        },
        {
            "name": "sat",
            "id": 144398,
            "type": 1,
            "sub_type": 0,
            "is_commerce": false,
            "description": ""
        },
        {
            "name": "study",
            "id": 73549,
            "type": 1,
            "sub_type": 0,
            "is_commerce": false,
            "description": ""
        },
        {
            "name": "school",
            "id": 3586,
            "type": 1,
            "sub_type": 0,
            "is_commerce": false,
            "description": ""
        },
        {
            "name": "math",
            "id": 137467,
            "type": 1,
            "sub_type": 0,
            "is_commerce": false,
            "description": ""
        },
        {
            "name": "bigbraintutor",
            "id": 7201548107580964906,
            "type": 1,
            "sub_type": 0,
            "is_commerce": false,
            "description": ""
        },
        {
            "name": "education",
            "id": 97277,
            "type": 1,
            "sub_type": 0,
            "is_commerce": false,
            "description": ""
        },
        {
            "name": "studytok",
            "id": 1621382854945957,
            "type": 1,
            "sub_type": 0,
            "is_commerce": false,
            "description": "Take a seat and study with TikTok."
        }
    ]
}